sphinx_tudelft_theme/__init__.py
sphinx_tudelft_theme/_version.py
sphinx_tudelft_theme/static/RobotoSlab-Regular.woff
sphinx_tudelft_theme/static/RobotoSlab-Regular.woff2
sphinx_tudelft_theme/static/TUD_favicon.svg
sphinx_tudelft_theme/static/TUDelft_logo_descriptor_rgb.png
sphinx_tudelft_theme/static/TUDelft_logo_descriptor_white.png
sphinx_tudelft_theme/static/sticky-logo.css
sphinx_tudelft_theme/static/tudelft_fonts.css
sphinx_tudelft_theme/static/tudelft_style.css
sphinx_tudelft_theme/static/tudelft_title.css
sphinx_tudelft_theme-1.2.2.dist-info/METADATA
sphinx_tudelft_theme-1.2.2.dist-info/WHEEL
sphinx_tudelft_theme-1.2.2.dist-info/licenses/LICENSE
sphinx_tudelft_theme-1.2.2.dist-info/RECORD
