Metadata-Version: 2.4
Name: sphinx-tudelft-theme
Version: 1.2.2
Summary: A custom Sphinx extension to apply TU Delft styling to a TeachBook
Author-email: Jakub Fręchowicz <j.s.frechowicz@student.tudelft.nl>
License: MIT License
License-File: LICENSE
Requires-Python: >=3.10
Requires-Dist: sphinx
Requires-Dist: sphinx-favicon
